caelus/__init__.py
caelus/py.typed
caelus/version.py
caelus/build/__init__.py
caelus/build/build.py
caelus/config/__init__.py
caelus/config/cmlenv.py
caelus/config/config.py
caelus/config/default_config.yaml
caelus/config/jinja2wrappers.py
caelus/fvmesh/__init__.py
caelus/fvmesh/_helpers.py
caelus/fvmesh/fvmesh.py
caelus/fvmesh/helpers.py
caelus/io/__init__.py
caelus/io/caelusdict.py
caelus/io/caeluslextab.py
caelus/io/caelusyacctab.py
caelus/io/dictfile.py
caelus/io/dtypes.py
caelus/io/lexer.py
caelus/io/parser.py
caelus/io/printer.py
caelus/post/__init__.py
caelus/post/logs.py
caelus/post/plots.py
caelus/post/funcobj/__init__.py
caelus/post/funcobj/forces.py
caelus/post/funcobj/funcobj.py
caelus/post/funcobj/functions.py
caelus/post/funcobj/residuals.py
caelus/post/funcobj/sampling.py
caelus/post/funcobj/volume_report.py
caelus/run/__init__.py
caelus/run/case.py
caelus/run/cmd.py
caelus/run/core.py
caelus/run/hpc_queue.py
caelus/run/jobstate.py
caelus/run/parametric.py
caelus/run/tasks.py
caelus/run/udf.py
caelus/scripts/__init__.py
caelus/scripts/caelus.py
caelus/scripts/caelus_sim.py
caelus/scripts/caelus_tutorials.py
caelus/scripts/core.py
caelus/templates/run/hpc_queue/hpc_queue.job.tmpl
caelus/utils/__init__.py
caelus/utils/coroutines.py
caelus/utils/env_module.py
caelus/utils/euclid.py
caelus/utils/osutils.py
caelus/utils/pyutils.py
caelus/utils/struct.py
caelus/utils/tojson.py
caelus/utils/vtk_helpers.py
py_caelus-5.0.0.dist-info/licenses/LICENSE.txt
py_caelus-5.0.0.dist-info/METADATA
py_caelus-5.0.0.dist-info/WHEEL
py_caelus-5.0.0.dist-info/entry_points.txt
py_caelus-5.0.0.dist-info/top_level.txt
py_caelus-5.0.0.dist-info/RECORD
